LICENSE
MANIFEST.in
README.md
setup.cfg
setup.py
cloud_governance/__init__.py
cloud_governance/aws/__init__.py
cloud_governance/aws/cost_expenditure/__init__.py
cloud_governance/aws/cost_expenditure/cost_report_policies.py
cloud_governance/aws/dynamodb_upload_data/__init__.py
cloud_governance/aws/dynamodb_upload_data/cloudtrail_to_dynamodb.py
cloud_governance/aws/dynamodb_upload_data/upload_data_to_dynamodb.py
cloud_governance/aws/tag_cluster/__init__.py
cloud_governance/aws/tag_cluster/remove_cluster_tags.py
cloud_governance/aws/tag_cluster/run_tag_cluster_resouces.py
cloud_governance/aws/tag_cluster/tag_cluster_operations.py
cloud_governance/aws/tag_cluster/tag_cluster_resouces.py
cloud_governance/aws/tag_non_cluster/__init__.py
cloud_governance/aws/tag_non_cluster/non_cluster_operations.py
cloud_governance/aws/tag_non_cluster/remove_non_cluster_tags.py
cloud_governance/aws/tag_non_cluster/run_tag_non_cluster_resources.py
cloud_governance/aws/tag_non_cluster/tag_non_cluster_resources.py
cloud_governance/aws/tag_non_cluster/update_na_tag_resources.py
cloud_governance/aws/tag_user/__init__.py
cloud_governance/aws/tag_user/iam_user_tags.py
cloud_governance/aws/tag_user/remove_user_tags.py
cloud_governance/aws/tag_user/run_tag_iam_user.py
cloud_governance/aws/tag_user/tag_iam_user.py
cloud_governance/aws/zombie_cluster/__init__.py
cloud_governance/aws/zombie_cluster/delete_ec2_resources.py
cloud_governance/aws/zombie_cluster/delete_iam_resources.py
cloud_governance/aws/zombie_cluster/delete_s3_resources.py
cloud_governance/aws/zombie_cluster/run_zombie_cluster_resources.py
cloud_governance/aws/zombie_cluster/validate_zombies.py
cloud_governance/aws/zombie_cluster/zombie_cluster_common_methods.py
cloud_governance/aws/zombie_non_cluster/__init__.py
cloud_governance/aws/zombie_non_cluster/run_zombie_non_cluster_policies.py
cloud_governance/aws/zombie_non_cluster/zombie_non_cluster_polices.py
cloud_governance/azure/__init__.py
cloud_governance_important_athiruma.egg-info/PKG-INFO
cloud_governance_important_athiruma.egg-info/SOURCES.txt
cloud_governance_important_athiruma.egg-info/dependency_links.txt
cloud_governance_important_athiruma.egg-info/not-zip-safe
cloud_governance_important_athiruma.egg-info/requires.txt
cloud_governance_important_athiruma.egg-info/top_level.txt